COPYRIGHT
LICENSE
MANIFEST.in
README
calendar.xml
setup.cfg
setup.py
tryton.cfg
./__init__.py
./caldav.py
./calendar.xml
./calendar_.py
./res.py
./tryton.cfg
./webdav.py
./locale/bg.po
./locale/ca.po
./locale/cs.po
./locale/de.po
./locale/es.po
./locale/fr.po
./locale/hu_HU.po
./locale/it_IT.po
./locale/ja_JP.po
./locale/lo.po
./locale/lt.po
./locale/nl.po
./locale/pl.po
./locale/pt_BR.po
./locale/ru.po
./locale/sl.po
./locale/zh_CN.po
./tests/__init__.py
./tests/scenario_calendar.py
./tests/test_calendar.py
./view/attendee_form.xml
./view/attendee_tree.xml
./view/calendar_form.xml
./view/calendar_tree.xml
./view/category_form.xml
./view/category_tree.xml
./view/event_form.xml
./view/event_tree.xml
./view/event_tree_occurence.xml
./view/exdate_form.xml
./view/exdate_tree.xml
./view/exrule_form.xml
./view/exrule_tree.xml
./view/location_form.xml
./view/location_tree.xml
./view/rdate_form.xml
./view/rdate_tree.xml
./view/rrule_form.xml
./view/rrule_tree.xml
locale/bg.po
locale/ca.po
locale/cs.po
locale/de.po
locale/es.po
locale/fr.po
locale/hu_HU.po
locale/it_IT.po
locale/ja_JP.po
locale/lo.po
locale/lt.po
locale/nl.po
locale/pl.po
locale/pt_BR.po
locale/ru.po
locale/sl.po
locale/zh_CN.po
trytond_calendar_webdav3.egg-info/PKG-INFO
trytond_calendar_webdav3.egg-info/SOURCES.txt
trytond_calendar_webdav3.egg-info/dependency_links.txt
trytond_calendar_webdav3.egg-info/entry_points.txt
trytond_calendar_webdav3.egg-info/not-zip-safe
trytond_calendar_webdav3.egg-info/requires.txt
trytond_calendar_webdav3.egg-info/top_level.txt
view/attendee_form.xml
view/attendee_tree.xml
view/calendar_form.xml
view/calendar_tree.xml
view/category_form.xml
view/category_tree.xml
view/event_form.xml
view/event_tree.xml
view/event_tree_occurence.xml
view/exdate_form.xml
view/exdate_tree.xml
view/exrule_form.xml
view/exrule_tree.xml
view/location_form.xml
view/location_tree.xml
view/rdate_form.xml
view/rdate_tree.xml
view/rrule_form.xml
view/rrule_tree.xml